OUTLIER101703038/Outlier.py
OUTLIER101703038-1.0.0.dist-info/LICENSE.txt
OUTLIER101703038-1.0.0.dist-info/METADATA
OUTLIER101703038-1.0.0.dist-info/WHEEL
OUTLIER101703038-1.0.0.dist-info/entry_points.txt
OUTLIER101703038-1.0.0.dist-info/top_level.txt
OUTLIER101703038-1.0.0.dist-info/RECORD
